<?xml version="1.0" encoding="UTF-8" standalone="no"?>
<Data>
  <Grid l="1" maxx="40" maxy="30" minx="0" miny="0" w="1"/>
  <Tasks>
    <Task release="1" retract="23" value="7" x="20.42985981791523" y="23.70605239191944"/>
    <Task release="1" retract="12" value="6" x="22.796756129365928" y="0.1910667435344915"/>
    <Task release="1" retract="14" value="5" x="32.01596455033144" y="22.739141720819127"/>
    <Task release="1" retract="23" value="3" x="15.881215618448547" y="4.095261321078052"/>
    <Task release="3" retract="28" value="3" x="7.841916339005572" y="28.91633462448203"/>
    <Task release="5" retract="15" value="6" x="33.02249681999008" y="6.738813765788765"/>
    <Task release="6" retract="19" value="4" x="35.80350077054872" y="4.584173276826991"/>
    <Task release="6" retract="18" value="2" x="21.71350347759393" y="13.622355607687322"/>
    <Task release="6" retract="27" value="9" x="23.09663728767001" y="14.656418505984764"/>
    <Task release="7" retract="27" value="2" x="30.845273996870937" y="27.229932874912855"/>
    <Task release="10" retract="25" value="1" x="14.93632177746283" y="14.603884932259813"/>
    <Task release="11" retract="40" value="7" x="37.92793898774756" y="17.550028280052537"/>
    <Task release="11" retract="38" value="3" x="6.866152261182545" y="12.540359957247583"/>
    <Task release="11" retract="36" value="6" x="37.62366428120871" y="7.897259247661248"/>
    <Task release="11" retract="39" value="8" x="22.465117958094257" y="8.238442196062286"/>
    <Task release="12" retract="41" value="2" x="4.161251916242841" y="17.586394439610736"/>
    <Task release="12" retract="38" value="4" x="6.631243114584167" y="2.2596180464500826"/>
    <Task release="14" retract="36" value="2" x="5.733438682528966" y="14.411239497996256"/>
    <Task release="14" retract="30" value="4" x="23.50280764448098" y="12.658935188872118"/>
    <Task release="14" retract="25" value="8" x="2.399649710527174" y="18.825146680924068"/>
    <Task release="16" retract="36" value="4" x="33.24380039051173" y="7.701323621592012"/>
    <Task release="16" retract="26" value="2" x="39.637558347708705" y="25.17057751786996"/>
    <Task release="19" retract="30" value="6" x="3.954875889499152" y="27.296203287205"/>
    <Task release="20" retract="42" value="9" x="19.5968972971888" y="25.97661493938118"/>
    <Task release="21" retract="41" value="8" x="25.018807842728712" y="17.39080393021401"/>
    <Task release="21" retract="50" value="7" x="22.557997510994152" y="15.851462983386185"/>
    <Task release="22" retract="38" value="1" x="5.4423178181137555" y="17.18696211158974"/>
    <Task release="23" retract="50" value="1" x="14.541468781512283" y="5.3318757644186165"/>
    <Task release="24" retract="39" value="5" x="33.11968700655525" y="3.417778359924805"/>
    <Task release="24" retract="38" value="6" x="21.883761358843156" y="26.192722453081593"/>
    <Task release="24" retract="44" value="8" x="9.786439985626911" y="28.87682965704142"/>
    <Task release="24" retract="50" value="9" x="22.247155196597248" y="12.791249465647311"/>
    <Task release="24" retract="44" value="4" x="16.19721760258659" y="24.221068996732168"/>
    <Task release="24" retract="45" value="2" x="18.188369704677953" y="29.8016672489182"/>
    <Task release="25" retract="46" value="4" x="21.670320277434815" y="12.894001080282246"/>
    <Task release="27" retract="37" value="1" x="22.672840745597497" y="15.603741561640692"/>
    <Task release="29" retract="49" value="7" x="20.266638279687786" y="24.60739024987548"/>
    <Task release="30" retract="40" value="4" x="8.65270882522951" y="29.463363487123402"/>
    <Task release="30" retract="53" value="8" x="19.914600531868103" y="23.60395415057512"/>
    <Task release="30" retract="47" value="3" x="8.202372020162748" y="6.576955490584462"/>
    <Task release="31" retract="56" value="8" x="28.507951637322392" y="17.21527172349159"/>
    <Task release="32" retract="59" value="8" x="26.37854599859355" y="10.584101816313904"/>
    <Task release="32" retract="47" value="8" x="12.921314830993156" y="3.1228630120659826"/>
    <Task release="33" retract="47" value="8" x="27.528862456013027" y="20.414950166551414"/>
    <Task release="33" retract="58" value="2" x="14.039946930002047" y="17.08761862355389"/>
    <Task release="36" retract="48" value="1" x="20.27021181800023" y="23.715139150023454"/>
    <Task release="37" retract="58" value="5" x="19.938500124096667" y="25.641380675396555"/>
    <Task release="38" retract="52" value="1" x="35.127624683168634" y="2.8834141413837857"/>
    <Task release="38" retract="55" value="1" x="11.650893269891434" y="8.563322817778186"/>
    <Task release="39" retract="60" value="3" x="39.47810220890928" y="7.581143033484707"/>
  </Tasks>
  <Workers>
    <Worker max="5" release="1" retract="12" x="27.55597924620301" y="18.089904431065683"/>
    <Worker max="5" release="13" retract="54" x="4.017145647844664" y="10.83480372290379"/>
    <Worker max="5" release="14" retract="27" x="19.883189940277525" y="20.78489129026221"/>
    <Worker max="4" release="23" retract="60" x="37.50870141212107" y="26.90656991328602"/>
    <Worker max="4" release="24" retract="67" x="38.590019376447934" y="3.6851436163135984"/>
    <Worker max="3" release="25" retract="72" x="6.443433210354184" y="3.4373153245092016"/>
    <Worker max="3" release="34" retract="64" x="17.506171006413012" y="23.005587587749396"/>
  </Workers>
</Data>
